LICENSE
README.md
setup.py
qube/__init__.py
qube/version.py
qube/drivers/ATM_delay_line.py
qube/drivers/Keysight_3458A.py
qube/drivers/Keysight_86100c.py
qube/drivers/Keysight_B2901A.py
qube/drivers/Keysight_E8257D.py
qube/drivers/Keysight_ENA.py
qube/drivers/Keysight_FieldFox.py
qube/drivers/Keysight_M8190A.py
qube/drivers/Keysight_M8195A.py
qube/drivers/Keysight_N1094A.py
qube/drivers/Keysight_PNA.py
qube/drivers/Lakeshore_Model_335.py
qube/drivers/Measurement_info.py
qube/drivers/NEEL_DAC.py
qube/drivers/NEEL_DAC_HE.py
qube/drivers/NEEL_DAC_JL.py
qube/drivers/NEEL_DAC_ST.py
qube/drivers/NI6216.py
qube/drivers/NI6343.py
qube/drivers/NI6733.py
qube/drivers/NI9239.py
qube/drivers/NITB4300.py
qube/drivers/RS_SMA100B.py
qube/drivers/RS_SMB100A.py
qube/drivers/SR7265.py
qube/drivers/SunJEM_LF_V2.py
qube/drivers/Tektronix_AWG7000.py
qube/drivers/ZI_MFLI.py
qube/drivers/__init__.py
qube/helpers/__init__.py
qube/helpers/data_conversion.py
qube/helpers/qcodes_data.py
qube/helpers/qcodes_layout.py
qube/helpers/qufox_layout.py
qube/layout/__init__.py
qube/layout/base.py
qube/layout/config.py
qube/layout/gds.py
qube/measurement/__init__.py
qube/measurement/content.py
qube/measurement/controls.py
qube/measurement/experiment.py
qube/measurement/sweep.py
qube/measurement/sweeper.py
qube/postprocess/__init__.py
qube/postprocess/axes.py
qube/postprocess/datafile.py
qube/postprocess/dataset.py
qube/postprocess/figures.py
qube/postprocess/postprocess.py
qube/utils/__init__.py
qube/utils/misc.py
qube/utils/path.py
qube/utils/units.py
qube_qcodes.egg-info/PKG-INFO
qube_qcodes.egg-info/SOURCES.txt
qube_qcodes.egg-info/dependency_links.txt
qube_qcodes.egg-info/top_level.txt