Metadata-Version: 2.1
Name: qube-qcodes
Version: 0.1.5
Summary: Useful tools for experiments performed by the group of Dr. Christopher Bauerle (CNRS Neel Institute, Grenoble)
Home-page: https://github.com/Junliang-Wang/qube
Author: Junliang WANG
Author-email: junliang.wang.w@gmail.com
License: BSD-3-Clause
Classifier: Programming Language :: Python :: 3
Classifier: License :: OSI Approved :: BSD License
Classifier: Operating System :: OS Independent
Classifier: Intended Audience :: Customer Service
Classifier: Intended Audience :: Developers
Classifier: Intended Audience :: Education
Classifier: Intended Audience :: Science/Research
Classifier: Natural Language :: English
Requires-Python: >=3.9
License-File: LICENSE
